{
  "strategy_params": {
    "asia_start": 1,
    "asia_end": 8,
    "trade_start": 9,
    "trade_end": 13,
    "min_asia_bars": 6,
    "max_late_entry_atr": 0.5,
    "atr_period": 14
  },
  "trade_management": {
    "partial_tp_r": 2.0,
    "partial_fraction": 0.5,
    "move_sl_to_breakeven": true,
    "trailing_stop_r": 1.5,
    "trailing_activate_r": 2.0,
    "remove_tp_when_trailing": true
  },
  "notes": "รอบ2: allowed_regimes=None (จากผลรวม 3TF) min_approvals=4 (wrong_entry 38%) | runner ชนะ: partial 2R + trail 1.5R ให้ +4435 (exp 13.65 PF 1.21) vs baseline +3196 (exp 9.83) — ดีขึ้นทุก regime | ประวัติ: partial 1R = -2011 (แย่), trailing 1R เพียว = +813 (แย่กว่า baseline) | รอบ4: ทดสอบ dd_targeting (cap1.15/floor0.6/hr0.5) แล้ว — M30 return ดีขึ้นนิดหน่อยแต่ DD แย่ลง, H1 return แย่ลง — สุทธิไม่คุ้ม ไม่ adopt ให้ทีมนี้ (ต่างจาก trend_pullback ที่ได้ผลชัดเจน) | รอบ9 full-devil(WF-guarded): hour_filter exp 14.37->18.51",
  "allowed_regimes": null,
  "blocked_hours": [
    11
  ],
  "min_approvals": 4,
  "risk": {
    "risk_per_trade_pct": 1.0,
    "max_daily_loss_pct": 3.0,
    "max_weekly_loss_pct": 6.0,
    "max_drawdown_pct": 20.0,
    "sizing_mode": "vol_scaled"
  },
  "strategy_review": {
    "edge": "สภาพคล่องพุ่งตอน London เปิดดันราคาออกจากกรอบเอเชียแล้ววิ่งต่อ",
    "best_market": "วันที่ London มีทิศทาง ทุก TF ที่ทดสอบ (H1/M30/M15)",
    "avoid_when": "วันกรอบเอเชียกว้างผิดปกติ / เข้าช้าหลัง 13:00"
  }
}